
{
    "message": "OK",
    "data": {
      "job_seekers": [
        {
          "id": 66311,
          "uuid": "d8f40520-c8b8-11e8-9ed8-fde5752954ef",
          "first_name": "Reynald",
          "last_name": "Porras Jr",
          "email": "brosnoiraspor@gmail.com",
          "phone_num": null,
          "gender": "",
          "age": 0,
          "birthdate": "1986-09-22",
          "address": null,
          "postal_code": null,
          "avatar": "https://media.licdn.com/dms/image/C5603AQHZMMZVx7muRA/profile-displayphoto-shrink_100_100/0?e=1544054400&v=beta&t=fAfJQojuq1L4A7ZGtmpNLhd1BRGC_sotn-VnlRMqSt8",
          "country_key": "ph",
          "region_key": null,
          "location_key": "iloilo_city",
          "website": null,
          "description": "Patience is a virtue",
          "xp_lvl_key": null,
          "employment_status_key": "",
          "referral_code": "reynaldojr.4fbc",
          "fb_user_id": null,
          "linkedin_user_id": "GlC2TucL4s",
          "is_restricted": false,
          "is_email_verify": false,
          "is_verify": false,
          "is_subscribe": true,
          "status_key": "active",
          "source": "web",
          "created_at": "2018-10-06 00:08:07",
          "updated_at": "2018-10-06 00:12:15",
          "active_key": 1,
          "is_visible": false,
          "xp_lvl": null,
          "latest_education": null,
          "latest_work_xp": null,
          "latest_preference": {
            "job_title_id": "410",
            "job_type": "Full-time",
            "country": "Philippines",
            "salary_range_to": 25000,
            "salary_range_from": 15000,
            "created_at": "2018-10-06 00:14:30",
            "industry": "Engineering",
            "industry_key": "engineering",
            "job_type_key": "full_time",
            "country_key": "ph",
            "updated_at": "2018-10-06 00:14:30",
            "user_id": 66311,
            "currency": null,
            "location": "Iloilo City",
            "id": 16792,
            "job_title": "ELECTRICAL ENGINEER",
            "location_key": "iloilo_city",
            "status_key": "active"
          },
          "recruiter_latest_work_xp": null,
          "country": "Philippines",
          "profile": {
            "percentage": 35,
            "incomplete": [
              "website",
              "work_xps",
              "education",
              "skills"
            ]
          },
          "location": "Iloilo City",
          "resumes": [
            {
              "filename": "CV_PORRASREYNALDOJRCV.doc",
              "is_active": 1,
              "updated_at": "2019-06-04 23:15:53",
              "user_id": 66311,
              "description": null,
              "is_parsed_es": 0,
              "created_at": "2018-10-06 00:13:21",
              "id": 6478,
              "deleted_at": null,
              "url": "https://assets.bossjob.com/users/66311/resume/pT3PrgwjQr2JlIchvsutf99aCdFiLDrUOf6qcU6T.doc",
              "status_key": "active"
            }
          ],
          "work_xps": [
            
          ],
          "educations": [
            
          ],
          "skills": null,
          "roles": [
            {
              "name": "job_seeker",
              "description": "Job seeker",
              "pivot": {
                "user_id": 66311,
                "role_id": 1
              },
              "id": 1,
              "display_name": "Job Seeker"
            }
          ],
          "additional_info": null,
          "user_created_at": "2018-10-06",
          "user_updated_at": "2018-10-06",
          "resumes_count": 1,
          "resume_technology": "Bachelor of Science in Electrical Engineering, 2012\nSEMINAR ATTENDED\nIn-house Seminars and Trainings (EPICS):\nConstruction Occupational Safety and Health\nBasic Fire Prevention and Safety\nElectrical Inspection, Audit and Safety\nIn-house Seminars and Trainings (ENGTECH):\nIDS Hi-Mod GPR \"Acquisition Unit and Post Processing Unit\"\nQualification for Radiation Protection Officers (RPO's)\nTemperature Measurement and Calibration Training\nForce and Torque Measurement and Calibration Training\nBalance and Weight Measurement and Calibration Training\nCAREER OBJECTIVE\nTo be a proactive member in a challenging environment that would utilize\nand further develop my skills that\nWould be beneficial to the company as well as to my personal growth.\nPROFESSIONAL PROFILE\nHas a 6 years of project supervision in a construction and maintenance\nmonitoring experience. Trained in handling different contractors and\nprojects for supervision to ensure work progress is met within the time\nframe. Responsible for actual monitoring on site to make sure it is in\naccordance with the Standard & Specification.\nPROFESSIONAL SKILLS\nKnowledgeable in using Microsoft office Word & Excel\nKnowledge in auto Cads\nResponsible hardworking result-oriented and able to work in a team\nWilling to work in graveyard shift and long distance travel if necessary\nHigh potential skills and able to deliver high performance as a result\nEager to learn and a fast learner, can apply skills immediately\nExcellent Team Player/Leader\nHigh adaptable to changes in work schedules, work environment and\nsituations\nCan handle stress and pressures as a result, being flexible\nTrained to work with minimal supervision\nLooking to settle for a long-term career\nEMPLOYMENT HISTORY\nElekins Power Innovations and Control Solutions Inc.\nSeptember 5, 2016 –Present\nElekins Power Innovations and Control Solutions Inc. specializes in\nengineering, construction management and construction of utility projects\nlike Residential Subdivision, Medical Facilities, Malls, Schools, Roads and\nCommercial Centers, Hotels etc.\nJOB TITLE: PROJECT IN-CHARGE-MEPFS\nDUTIES AND RESPONSIBILITIES:\nSupervise all related work activities and assigned tasks being done on\nsite based on submitted and approved Work Sequence and Methodology.\nInterprets and executes plans and Specifications\nChecks work design and technical specifications if implemented correctly\non site.\nResolves the cause of delay in target schedule and problems related to\nwork activity.\nCoordinates and monitors subcontractor works on proper execution and\ncompliance to Quality plan.\nFurnishes subcontractors the plans / details needed as well as informing\nthem of the changes or additive/deductive\nWorks on site.\nEvaluates and checks work accomplishments versus submitted billings.\nCoordinates the requisition, issuances and the timely delivery of\nrequired materials on site.\nEnsures that all materials to be installed comply with the approved\nsubmittals and tests.\nConducts \"time and motion study\" and documents man hour productivity on\nassigned scope of work.\nEnsures the proper stock filling and safekeeping of the company-owned\nequipment/tools.\nPrepares electrical plans and As-Built plan.\nEnforces the implementation of quality plans and objectives of the\nproject.\nPrepares quantity take off and bill of quantities for bidding\nImplements all environmental, health and safety rules as well as security\nregulations within my area of assignment\nENGINEERING TECHNOLOGY (ENG-TECH) RIYADH SAUDI ARABIA\nJanuary 2014-January 2016\nInstrumentation Calibration and maintenance services MEPF Engineers,\nroads and highway.\nJOB TITLE: INSTRUMENTATION ENGINEER\nDUTIES AND RESPONSIBILITIES:\nCalibration of all electrical equipment's ensuring compliance with safety\nrequirements and as per standards.\nCoordinate with Mechanical, civil Engineers, Discuss technical standards\nuse for equipment calibration for successful completion of projects.\nEnsure all materials are calibrated in standard process\nFollowing higher management time schedule instructions and advices,\nreporting work field conditions problems and status to higher management,\nfollowing activities of other departments in site.\nConduct inspections of equipment for preventive maintenance.\nPrepare documentation for calibrated instrument\nChecking the drawings and document's used at site for approvals compliance\nwith project requirements.\nAssist and coordinate the preparation of the final handing over documents,\ntesting and commissioning reports, Maintaining records and archives to\ncompany standards.\nUsing hand tools and power tools.\nDiagnose malfunctioning systems, apparatus, and components, using test\nequipment and hand tools, to locate the cause of a breakdown and correct\nthe problem.\nInspect electrical systems, equipment, and components to identify hazards,\ndefects, and the need for adjustment or repair, and to ensure compliance\nwith codes.\nAdvise management on whether continued operation of equipment could be\nhazardous.\nTest electrical systems and continuity of circuits in electrical wiring,\nequipment, and fixtures, using testing devices such as ohmmeters,\nvoltmeters, and oscilloscopes, to ensure compatibility and safety of\nsystem.\nSupervising works in the fields of electrical area.\nOperates and conduct scanning on site using Hi-Mod Ground Penetrating Radar\n(GPR).\nProcessing the data taken from GPR using the IDS system \"Acquisition Unit\nand Post Processing Unit.\nPlotting of any utilities using autocad from the processed acquisition.\nMaking reports, conclusions and recommendation through evaluations of the\nprocessed data.\nLBCarmelo Engineering\nOctober 2012-November 2013\nElectrical Contractor based on Iloilo province, composed of Electrical\nEngineers, for Electrical designs, site implementation, testing and\ncommissioning.\nJOB TITLE: Project Engineer\nDUTIES AND RESPONSIBILITIES:\nPreparation of Electrical deigns for residential, commercial and\nindustrials buildings.\nPreparation of Auto-cad drawings, for construction up to As-Built plan.\nPreparation of load computation, voltage drop and short circuit calculation\nbased on standards.\nSite visit and inspection during construction and meeting with clients\nPreparation of Bill of materials and cost estimates.\nChecking the drawings and document's used at site for approvals compliance\nwith project requirements.\nDocumentation and encoding.\nPrepares quantity take off and bill of quantities for bidding\nCost and Estimation\nChecks work design and technical specifications.\nMeeting with clients\nEvaluates and checks work accomplishments versus submitted billings.\nCoordinates the requisition, issuances and the timely delivery of\nrequired materials on site.\nEnsures that all materials to be installed comply with the approved\nsubmittals and tests.\nConducts \"time and motion study\" and documents man hour productivity on\nassigned scope of work.\nEnsures the proper stock filling and safekeeping of the company-owned\nequipment/tools.\nEnforces the implementation of quality plans and objectives of the\nproject.\nPrepares quantity take off and bill of quantities for bidding.\nSUPERVISE AND MONITORING FOR ELECTRICAL WORKS\nInspection of installation transformer up to 1000KVA to LV switchgear\nsubstation, Emergency power or Generator termination synchronizing panel ,\nAutomatic Transfer Switch, Main Distribution Panel, Distribution Panel\nPower Panel, Lighting Panel.\nInternal and External Decorative light fixtures, Illumination and Dimming\nsystem, Power receptacles, Cable routing, Earthing, Cable trays, Panel\nBoard and Building Management System.\nConduct testing and commissioning of electrical power system insulation and\ncontinuity test motors, pumps and devices.\nILOILO ELECTRIC COMPANY II\nON THE JOB TRAINEE – UTILITY COMPANY\nApril 2010 – May 2010\nJOB TITLE: On-the-Job Trainee\nDUTIES AND RESPONSIBILITIES:\nAssist the field/site Electrical Engineers in various electrical\nmaintenance and programming.\nMaintain the electrical supplies on the sites.\nCheck the electrical wirings and connections on the different departments\nof the Plant site.\nReplaces electrical supplies not functioning well.\nMaintain the safety of the electrical connections and observe one's safety\nall the time\nREFERENCES:\nEngr. June A Porras\nQuantity Surveyor\n09095709278\nEngr. Alex F. Pida\nElectrical Engineer\n09992290844\nEngr. Roberto G. Barela\nQuantity Surveyor\n09959046957\nREYNALDO L. PORRAS JR.\nApplicant\n-----------------------\nMrPorras CURRICULUM VITAE . 09273257939\nPage 4",
          "resume_education": "AL BACKGROUND\nWESTERN INSTITUTE OF TECHNOLOGY\nBachelor of Science in Electrical Engineering, 2012\nSEMINAR ATTENDED\nIn-house Seminars and Trainings (EPICS):\nConstruction Occupational Safety and Health\nBasic Fire Prevention and Safety\nElectrical Inspection, Audit and Safety\nIn-house Seminars and Trainings (ENGTECH):\nIDS Hi-Mod GPR \"Acquisition Unit and Post Processing Unit\"\nQualification for Radiation Protection Officers (RPO's)\nTemperature Measurement and Calibration Training\nForce and Torque Measurement and Calibration Training\nBalance and Weight Measurement and Calibration Training\nCAREER OBJECTIVE\nTo be a proactive member in a challenging environment that would utilize\nand further develop my skills that\nWould be beneficial to the company as well as to my personal growth.\nPROFESSIONAL PROFILE\nHas a 6 years of project supervision in a construction and maintenance\nmonitoring experience. Trained in handling different contractors and\nprojects for supervision to ensure work progress is met within the time\nframe. Responsible for actual monitoring on site to make sure it is in\naccordance with the Standard & Specification.\nPROFESSIONAL SKILLS\nKnowledgeable in using Microsoft office Word & Excel\nKnowledge in auto Cads\nResponsible hardworking result-oriented and able to work in a team\nWilling to work in graveyard shift and long distance travel if necessary\nHigh potential skills and able to deliver high performance as a result\nEager to learn and a fast learner, can apply skills immediately\nExcellent Team Player/Leader\nHigh adaptable to changes in work schedules, work environment and\nsituations\nCan handle stress and pressures as a result, being flexible\nTrained to work with minimal supervision\nLooking to settle for a long-term career\nEMPLOYMENT HISTORY\nElekins Power Innovations and Control Solutions Inc.\nSeptember 5, 2016 –Present\nElekins Power Innovations and Control Solutions Inc. specializes in\nengineering, construction management and construction of utility projects\nlike Residential Subdivision, Medical Facilities, Malls, Schools, Roads and\nCommercial Centers, Hotels etc.\nJOB TITLE: PROJECT IN-CHARGE-MEPFS\nDUTIES AND RESPONSIBILITIES:\nSupervise all related work activities and assigned tasks being done on\nsite based on submitted and approved Work Sequence and Methodology.\nInterprets and executes plans and Specifications\nChecks work design and technical specifications if implemented correctly\non site.\nResolves the cause of delay in target schedule and problems related to\nwork activity.\nCoordinates and monitors subcontractor works on proper execution and\ncompliance to Quality plan.\nFurnishes subcontractors the plans / details needed as well as informing\nthem of the changes or additive/deductive\nWorks on site.\nEvaluates and checks work accomplishments versus submitted billings.\nCoordinates the requisition, issuances and the timely delivery of\nrequired materials on site.\nEnsures that all materials to be installed comply with the approved\nsubmittals and tests.\nConducts \"time and motion study\" and documents man hour productivity on\nassigned scope of work.\nEnsures the proper stock filling and safekeeping of the company-owned\nequipment/tools.\nPrepares electrical plans and As-Built plan.\nEnforces the implementation of quality plans and objectives of the\nproject.\nPrepares quantity take off and bill of quantities for bidding\nImplements all environmental, health and safety rules as well as security\nregulations within my area of assignment\nENGINEERING TECHNOLOGY (ENG-TECH) RIYADH SAUDI ARABIA\nJanuary 2014-January 2016\nInstrumentation Calibration and maintenance services MEPF Engineers,\nroads and highway.\nJOB TITLE: INSTRUMENTATION ENGINEER\nDUTIES AND RESPONSIBILITIES:\nCalibration of all electrical equipment's ensuring compliance with safety\nrequirements and as per standards.\nCoordinate with Mechanical, civil Engineers, Discuss technical standards\nuse for equipment calibration for successful completion of projects.\nEnsure all materials are calibrated in standard process\nFollowing higher management time schedule instructions and advices,\nreporting work field conditions problems and status to higher management,\nfollowing activities of other departments in site.\nConduct inspections of equipment for preventive maintenance.\nPrepare documentation for calibrated instrument\nChecking the drawings and document's used at site for approvals compliance\nwith project requirements.\nAssist and coordinate the preparation of the final handing over documents,\ntesting and commissioning reports, Maintaining records and archives to\ncompany standards.\nUsing hand tools and power tools.\nDiagnose malfunctioning systems, apparatus, and components, using test\nequipment and hand tools, to locate the cause of a breakdown and correct\nthe problem.\nInspect electrical systems, equipment, and components to identify hazards,\ndefects, and the need for adjustment or repair, and to ensure compliance\nwith codes.\nAdvise management on whether continued operation of equipment could be\nhazardous.\nTest electrical systems and continuity of circuits in electrical wiring,\nequipment, and fixtures, using testing devices such as ohmmeters,\nvoltmeters, and oscilloscopes, to ensure compatibility and safety of\nsystem.\nSupervising works in the fields of electrical area.\nOperates and conduct scanning on site using Hi-Mod Ground Penetrating Radar\n(GPR).\nProcessing the data taken from GPR using the IDS system \"Acquisition Unit\nand Post Processing Unit.\nPlotting of any utilities using autocad from the processed acquisition.\nMaking reports, conclusions and recommendation through evaluations of the\nprocessed data.\nLBCarmelo Engineering\nOctober 2012-November 2013\nElectrical Contractor based on Iloilo province, composed of Electrical\nEngineers, for Electrical designs, site implementation, testing and\ncommissioning.\nJOB TITLE: Project Engineer\nDUTIES AND RESPONSIBILITIES:\nPreparation of Electrical deigns for residential, commercial and\nindustrials buildings.\nPreparation of Auto-cad drawings, for construction up to As-Built plan.\nPreparation of load computation, voltage drop and short circuit calculation\nbased on standards.\nSite visit and inspection during construction and meeting with clients\nPreparation of Bill of materials and cost estimates.\nChecking the drawings and document's used at site for approvals compliance\nwith project requirements.\nDocumentation and encoding.\nPrepares quantity take off and bill of quantities for bidding\nCost and Estimation\nChecks work design and technical specifications.\nMeeting with clients\nEvaluates and checks work accomplishments versus submitted billings.\nCoordinates the requisition, issuances and the timely delivery of\nrequired materials on site.\nEnsures that all materials to be installed comply with the approved\nsubmittals and tests.\nConducts \"time and motion study\" and documents man hour productivity on\nassigned scope of work.\nEnsures the proper stock filling and safekeeping of the company-owned\nequipment/tools.\nEnforces the implementation of quality plans and objectives of the\nproject.\nPrepares quantity take off and bill of quantities for bidding.\nSUPERVISE AND MONITORING FOR ELECTRICAL WORKS\nInspection of installation transformer up to 1000KVA to LV switchgear\nsubstation, Emergency power or Generator termination synchronizing panel ,\nAutomatic Transfer Switch, Main Distribution Panel, Distribution Panel\nPower Panel, Lighting Panel.\nInternal and External Decorative light fixtures, Illumination and Dimming\nsystem, Power receptacles, Cable routing, Earthing, Cable trays, Panel\nBoard and Building Management System.\nConduct testing and commissioning of electrical power system insulation and\ncontinuity test motors, pumps and devices.\nILOILO ELECTRIC COMPANY II\nON THE JOB TRAINEE – UTILITY COMPANY\nApril 2010 – May 2010\nJOB TITLE: On-the-Job Trainee\nDUTIES AND RESPONSIBILITIES:\nAssist the field/site Electrical Engineers in various electrical\nmaintenance and programming.\nMaintain the electrical supplies on the sites.\nCheck the electrical wirings and connections on the different departments\nof the Plant site.\nReplaces electrical supplies not functioning well.\nMaintain the safety of the electrical connections and observe one's safety\nall the time\nREFERENCES:\nEngr. June A Porras\nQuantity Surveyor\n09095709278\nEngr. Alex F. Pida\nElectrical Engineer\n09992290844\nEngr. Roberto G. Barela\nQuantity Surveyor\n09959046957\nREYNALDO L. PORRAS JR.\nApplicant\n-----------------------\nMrPorras CURRICULUM VITAE . 09273257939\nPage 4",
          "resume_skills": "Bachelor of Science in Electrical Engineering, 2012\nSEMINAR ATTENDED\nIn-house Seminars and Trainings (EPICS):\nConstruction Occupational Safety and Health\nBasic Fire Prevention and Safety\nElectrical Inspection, Audit and Safety\nIn-house Seminars and Trainings (ENGTECH):\nIDS Hi-Mod GPR \"Acquisition Unit and Post Processing Unit\"\nQualification for Radiation Protection Officers (RPO's)\nTemperature Measurement and Calibration Training\nForce and Torque Measurement and Calibration Training\nBalance and Weight Measurement and Calibration Training\nCAREER OBJECTIVE\nTo be a proactive member in a challenging environment that would utilize\nand further develop my skills that\nWould be beneficial to the company as well as to my personal growth.\nPROFESSIONAL PROFILE\nHas a 6 years of project supervision in a construction and maintenance\nmonitoring experience. Trained in handling different contractors and\nprojects for supervision to ensure work progress is met within the time\nframe. Responsible for actual monitoring on site to make sure it is in\naccordance with the Standard & Specification.\nPROFESSIONAL SKILLS\nKnowledgeable in using Microsoft office Word & Excel\nKnowledge in auto Cads\nResponsible hardworking result-oriented and able to work in a team\nWilling to work in graveyard shift and long distance travel if necessary\nHigh potential skills and able to deliver high performance as a result\nEager to learn and a fast learner, can apply skills immediately\nExcellent Team Player/Leader\nHigh adaptable to changes in work schedules, work environment and\nsituations\nCan handle stress and pressures as a result, being flexible\nTrained to work with minimal supervision\nLooking to settle for a long-term career\nEMPLOYMENT HISTORY\nElekins Power Innovations and Control Solutions Inc.\nSeptember 5, 2016 –Present\nElekins Power Innovations and Control Solutions Inc. specializes in\nengineering, construction management and construction of utility projects\nlike Residential Subdivision, Medical Facilities, Malls, Schools, Roads and\nCommercial Centers, Hotels etc.\nJOB TITLE: PROJECT IN-CHARGE-MEPFS\nDUTIES AND RESPONSIBILITIES:\nSupervise all related work activities and assigned tasks being done on\nsite based on submitted and approved Work Sequence and Methodology.\nInterprets and executes plans and Specifications\nChecks work design and technical specifications if implemented correctly\non site.\nResolves the cause of delay in target schedule and problems related to\nwork activity.\nCoordinates and monitors subcontractor works on proper execution and\ncompliance to Quality plan.\nFurnishes subcontractors the plans / details needed as well as informing\nthem of the changes or additive/deductive\nWorks on site.\nEvaluates and checks work accomplishments versus submitted billings.\nCoordinates the requisition, issuances and the timely delivery of\nrequired materials on site.\nEnsures that all materials to be installed comply with the approved\nsubmittals and tests.\nConducts \"time and motion study\" and documents man hour productivity on\nassigned scope of work.\nEnsures the proper stock filling and safekeeping of the company-owned\nequipment/tools.\nPrepares electrical plans and As-Built plan.\nEnforces the implementation of quality plans and objectives of the\nproject.\nPrepares quantity take off and bill of quantities for bidding\nImplements all environmental, health and safety rules as well as security\nregulations within my area of assignment\nENGINEERING TECHNOLOGY (ENG-TECH) RIYADH SAUDI ARABIA\nJanuary 2014-January 2016\nInstrumentation Calibration and maintenance services MEPF Engineers,\nroads and highway.\nJOB TITLE: INSTRUMENTATION ENGINEER\nDUTIES AND RESPONSIBILITIES:\nCalibration of all electrical equipment's ensuring compliance with safety\nrequirements and as per standards.\nCoordinate with Mechanical, civil Engineers, Discuss technical standards\nuse for equipment calibration for successful completion of projects.\nEnsure all materials are calibrated in standard process\nFollowing higher management time schedule instructions and advices,\nreporting work field conditions problems and status to higher management,\nfollowing activities of other departments in site.\nConduct inspections of equipment for preventive maintenance.\nPrepare documentation for calibrated instrument\nChecking the drawings and document's used at site for approvals compliance\nwith project requirements.\nAssist and coordinate the preparation of the final handing over documents,\ntesting and commissioning reports, Maintaining records and archives to\ncompany standards.\nUsing hand tools and power tools.\nDiagnose malfunctioning systems, apparatus, and components, using test\nequipment and hand tools, to locate the cause of a breakdown and correct\nthe problem.\nInspect electrical systems, equipment, and components to identify hazards,\ndefects, and the need for adjustment or repair, and to ensure compliance\nwith codes.\nAdvise management on whether continued operation of equipment could be\nhazardous.\nTest electrical systems and continuity of circuits in electrical wiring,\nequipment, and fixtures, using testing devices such as ohmmeters,\nvoltmeters, and oscilloscopes, to ensure compatibility and safety of\nsystem.\nSupervising works in the fields of electrical area.\nOperates and conduct scanning on site using Hi-Mod Ground Penetrating Radar\n(GPR).\nProcessing the data taken from GPR using the IDS system \"Acquisition Unit\nand Post Processing Unit.\nPlotting of any utilities using autocad from the processed acquisition.\nMaking reports, conclusions and recommendation through evaluations of the\nprocessed data.\nLBCarmelo Engineering\nOctober 2012-November 2013\nElectrical Contractor based on Iloilo province, composed of Electrical\nEngineers, for Electrical designs, site implementation, testing and\ncommissioning.\nJOB TITLE: Project Engineer\nDUTIES AND RESPONSIBILITIES:\nPreparation of Electrical deigns for residential, commercial and\nindustrials buildings.\nPreparation of Auto-cad drawings, for construction up to As-Built plan.\nPreparation of load computation, voltage drop and short circuit calculation\nbased on standards.\nSite visit and inspection during construction and meeting with clients\nPreparation of Bill of materials and cost estimates.\nChecking the drawings and document's used at site for approvals compliance\nwith project requirements.\nDocumentation and encoding.\nPrepares quantity take off and bill of quantities for bidding\nCost and Estimation\nChecks work design and technical specifications.\nMeeting with clients\nEvaluates and checks work accomplishments versus submitted billings.\nCoordinates the requisition, issuances and the timely delivery of\nrequired materials on site.\nEnsures that all materials to be installed comply with the approved\nsubmittals and tests.\nConducts \"time and motion study\" and documents man hour productivity on\nassigned scope of work.\nEnsures the proper stock filling and safekeeping of the company-owned\nequipment/tools.\nEnforces the implementation of quality plans and objectives of the\nproject.\nPrepares quantity take off and bill of quantities for bidding.\nSUPERVISE AND MONITORING FOR ELECTRICAL WORKS\nInspection of installation transformer up to 1000KVA to LV switchgear\nsubstation, Emergency power or Generator termination synchronizing panel ,\nAutomatic Transfer Switch, Main Distribution Panel, Distribution Panel\nPower Panel, Lighting Panel.\nInternal and External Decorative light fixtures, Illumination and Dimming\nsystem, Power receptacles, Cable routing, Earthing, Cable trays, Panel\nBoard and Building Management System.\nConduct testing and commissioning of electrical power system insulation and\ncontinuity test motors, pumps and devices.\nILOILO ELECTRIC COMPANY II\nON THE JOB TRAINEE – UTILITY COMPANY\nApril 2010 – May 2010\nJOB TITLE: On-the-Job Trainee\nDUTIES AND RESPONSIBILITIES:\nAssist the field/site Electrical Engineers in various electrical\nmaintenance and programming.\nMaintain the electrical supplies on the sites.\nCheck the electrical wirings and connections on the different departments\nof the Plant site.\nReplaces electrical supplies not functioning well.\nMaintain the safety of the electrical connections and observe one's safety\nall the time\nREFERENCES:\nEngr. June A Porras\nQuantity Surveyor\n09095709278\nEngr. Alex F. Pida\nElectrical Engineer\n09992290844\nEngr. Roberto G. Barela\nQuantity Surveyor\n09959046957\nREYNALDO L. PORRAS JR.\nApplicant\n-----------------------\nMrPorras CURRICULUM VITAE . 09273257939\nPage 4Knowledgeable in using Microsoft office Word & Excel\nKnowledge in auto Cads\nResponsible hardworking result-oriented and able to work in a team\nWilling to work in graveyard shift and long distance travel if necessary\nHigh potential skills and able to deliver high performance as a result\nEager to learn and a fast learner, can apply skills immediately\nExcellent Team Player/Leader\nHigh adaptable to changes in work schedules, work environment and\nsituations\nCan handle stress and pressures as a result, being flexible\nTrained to work with minimal supervision\nLooking to settle for a long-term career\nEMPLOYMENT HISTORY\nElekins Power Innovations and Control Solutions Inc.\nSeptember 5, 2016 –Present\nElekins Power Innovations and Control Solutions Inc. specializes in\nengineering, construction management and construction of utility projects\nlike Residential Subdivision, Medical Facilities, Malls, Schools, Roads and\nCommercial Centers, Hotels etc.\nJOB TITLE: PROJECT IN-CHARGE-MEPFS\nDUTIES AND RESPONSIBILITIES:\nSupervise all related work activities and assigned tasks being done on\nsite based on submitted and approved Work Sequence and Methodology.\nInterprets and executes plans and Specifications\nChecks work design and technical specifications if implemented correctly\non site.\nResolves the cause of delay in target schedule and problems related to\nwork activity.\nCoordinates and monitors subcontractor works on proper execution and\ncompliance to Quality plan.\nFurnishes subcontractors the plans / details needed as well as informing\nthem of the changes or additive/deductive\nWorks on site.\nEvaluates and checks work accomplishments versus submitted billings.\nCoordinates the requisition, issuances and the timely delivery of\nrequired materials on site.\nEnsures that all materials to be installed comply with the approved\nsubmittals and tests.\nConducts \"time and motion study\" and documents man hour productivity on\nassigned scope of work.\nEnsures the proper stock filling and safekeeping of the company-owned\nequipment/tools.\nPrepares electrical plans and As-Built plan.\nEnforces the implementation of quality plans and objectives of the\nproject.\nPrepares quantity take off and bill of quantities for bidding\nImplements all environmental, health and safety rules as well as security\nregulations within my area of assignment\nENGINEERING TECHNOLOGY (ENG-TECH) RIYADH SAUDI ARABIA\nJanuary 2014-January 2016\nInstrumentation Calibration and maintenance services MEPF Engineers,\nroads and highway.\nJOB TITLE: INSTRUMENTATION ENGINEER\nDUTIES AND RESPONSIBILITIES:\nCalibration of all electrical equipment's ensuring compliance with safety\nrequirements and as per standards.\nCoordinate with Mechanical, civil Engineers, Discuss technical standards\nuse for equipment calibration for successful completion of projects.\nEnsure all materials are calibrated in standard process\nFollowing higher management time schedule instructions and advices,\nreporting work field conditions problems and status to higher management,\nfollowing activities of other departments in site.\nConduct inspections of equipment for preventive maintenance.\nPrepare documentation for calibrated instrument\nChecking the drawings and document's used at site for approvals compliance\nwith project requirements.\nAssist and coordinate the preparation of the final handing over documents,\ntesting and commissioning reports, Maintaining records and archives to\ncompany standards.\nUsing hand tools and power tools.\nDiagnose malfunctioning systems, apparatus, and components, using test\nequipment and hand tools, to locate the cause of a breakdown and correct\nthe problem.\nInspect electrical systems, equipment, and components to identify hazards,\ndefects, and the need for adjustment or repair, and to ensure compliance\nwith codes.\nAdvise management on whether continued operation of equipment could be\nhazardous.\nTest electrical systems and continuity of circuits in electrical wiring,\nequipment, and fixtures, using testing devices such as ohmmeters,\nvoltmeters, and oscilloscopes, to ensure compatibility and safety of\nsystem.\nSupervising works in the fields of electrical area.\nOperates and conduct scanning on site using Hi-Mod Ground Penetrating Radar\n(GPR).\nProcessing the data taken from GPR using the IDS system \"Acquisition Unit\nand Post Processing Unit.\nPlotting of any utilities using autocad from the processed acquisition.\nMaking reports, conclusions and recommendation through evaluations of the\nprocessed data.\nLBCarmelo Engineering\nOctober 2012-November 2013\nElectrical Contractor based on Iloilo province, composed of Electrical\nEngineers, for Electrical designs, site implementation, testing and\ncommissioning.\nJOB TITLE: Project Engineer\nDUTIES AND RESPONSIBILITIES:\nPreparation of Electrical deigns for residential, commercial and\nindustrials buildings.\nPreparation of Auto-cad drawings, for construction up to As-Built plan.\nPreparation of load computation, voltage drop and short circuit calculation\nbased on standards.\nSite visit and inspection during construction and meeting with clients\nPreparation of Bill of materials and cost estimates.\nChecking the drawings and document's used at site for approvals compliance\nwith project requirements.\nDocumentation and encoding.\nPrepares quantity take off and bill of quantities for bidding\nCost and Estimation\nChecks work design and technical specifications.\nMeeting with clients\nEvaluates and checks work accomplishments versus submitted billings.\nCoordinates the requisition, issuances and the timely delivery of\nrequired materials on site.\nEnsures that all materials to be installed comply with the approved\nsubmittals and tests.\nConducts \"time and motion study\" and documents man hour productivity on\nassigned scope of work.\nEnsures the proper stock filling and safekeeping of the company-owned\nequipment/tools.\nEnforces the implementation of quality plans and objectives of the\nproject.\nPrepares quantity take off and bill of quantities for bidding.\nSUPERVISE AND MONITORING FOR ELECTRICAL WORKS\nInspection of installation transformer up to 1000KVA to LV switchgear\nsubstation, Emergency power or Generator termination synchronizing panel ,\nAutomatic Transfer Switch, Main Distribution Panel, Distribution Panel\nPower Panel, Lighting Panel.\nInternal and External Decorative light fixtures, Illumination and Dimming\nsystem, Power receptacles, Cable routing, Earthing, Cable trays, Panel\nBoard and Building Management System.\nConduct testing and commissioning of electrical power system insulation and\ncontinuity test motors, pumps and devices.\nILOILO ELECTRIC COMPANY II\nON THE JOB TRAINEE – UTILITY COMPANY\nApril 2010 – May 2010\nJOB TITLE: On-the-Job Trainee\nDUTIES AND RESPONSIBILITIES:\nAssist the field/site Electrical Engineers in various electrical\nmaintenance and programming.\nMaintain the electrical supplies on the sites.\nCheck the electrical wirings and connections on the different departments\nof the Plant site.\nReplaces electrical supplies not functioning well.\nMaintain the safety of the electrical connections and observe one's safety\nall the time\nREFERENCES:\nEngr. June A Porras\nQuantity Surveyor\n09095709278\nEngr. Alex F. Pida\nElectrical Engineer\n09992290844\nEngr. Roberto G. Barela\nQuantity Surveyor\n09959046957\nREYNALDO L. PORRAS JR.\nApplicant\n-----------------------\nMrPorras CURRICULUM VITAE . 09273257939\nPage 4",
          "device_type": null,
          "is_resume_parsed": 0,
          "last_active_at": {
            "date": "2019-06-04 23:15:54.098279",
            "timezone": "Asia/Singapore",
            "timezone_type": 3
          },
          "google_user_id": null,
          "last_login_ip": null,
          "device_os": null,
          "landing_url": null,
          "google_token": null,
          "is_unlock": true,
          "resume_keyword_count": 0,
          "profile_keyword_count": 0
        },
        {
          "id": 65896,
          "uuid": "108178e0-c781-11e8-9978-2920d867852e",
          "first_name": "Mafalda",
          "last_name": "Klein",
          "email": "admin@rightworkph.com",
          "phone_num": "9186067628",
          "gender": "",
          "age": 0,
          "birthdate": null,
          "address": null,
          "postal_code": null,
          "avatar": "https://fakeimg.pl/300x300/D6D9DC/4D4D4D/?text=MK&font_size=150&retina=1&font=noto",
          "country_key": "ph",
          "region_key": null,
          "location_key": null,
          "website": null,
          "description": null,
          "xp_lvl_key": null,
          "employment_status_key": "",
          "referral_code": "mafalda86cb20a5",
          "fb_user_id": null,
          "linkedin_user_id": null,
          "is_restricted": false,
          "is_email_verify": false,
          "is_verify": false,
          "is_subscribe": false,
          "status_key": "active",
          "source": "web",
          "created_at": "2018-10-04 10:56:17",
          "updated_at": "2018-10-04 10:56:17",
          "active_key": 1,
          "is_visible": true,
          "xp_lvl": null,
          "latest_education": null,
          "latest_work_xp": null,
          "latest_preference": {
            "id": 16734,
            "user_id": 65896,
            "job_title_id": null,
            "job_title": "RIGHTWORK PH ILOILO",
            "location_key": "iloilo_city",
            "salary_range_from": 30000,
            "salary_range_to": 35000,
            "currency": null,
            "job_type_key": "freelance",
            "industry_key": "bpo",
            "country_key": "ph",
            "status_key": "active",
            "created_at": "2018-10-04 10:59:45",
            "updated_at": "2018-10-04 11:09:02",
            "location": "Iloilo City",
            "job_type": "Freelance",
            "country": "Philippines",
            "industry": "BPO"
          },
          "recruiter_latest_work_xp": null,
          "country": "Philippines",
          "profile": {
            "percentage": 25,
            "incomplete": [
              "avatar",
              "basic_info",
              "work_xps",
              "education",
              "skills"
            ]
          },
          "location": null,
          "resumes": [
            {
              "filename": "logo ph online.webp",
              "is_active": 1,
              "updated_at": "2019-06-04 23:15:21",
              "user_id": 65896,
              "description": null,
              "is_parsed_es": 0,
              "created_at": "2018-10-04 11:07:04",
              "id": 6328,
              "deleted_at": null,
              "url": "https://assets.bossjob.com/users/65896/resume/mZREnjzHzOLvwIAXPV3NDmwDnlt0oJWAShOsJE6W.webp",
              "status_key": "active"
            }
          ],
          "work_xps": [
            
          ],
          "educations": [
            
          ],
          "skills": null,
          "resumes_count": 1,
          "roles": [
            {
              "name": "job_seeker",
              "description": "Job seeker",
              "pivot": {
                "user_id": 65896,
                "role_id": 1
              },
              "id": 1,
              "display_name": "Job Seeker"
            }
          ],
          "additional_info": null,
          "user_created_at": "2018-10-04",
          "user_updated_at": "2018-10-04",
          "device_type": null,
          "is_resume_parsed": 0,
          "last_active_at": {
            "date": "2019-06-04 23:15:21.860737",
            "timezone": "Asia/Singapore",
            "timezone_type": 3
          },
          "google_user_id": null,
          "last_login_ip": null,
          "device_os": null,
          "landing_url": null,
          "google_token": null,
          "is_unlock": true,
          "resume_keyword_count": 0,
          "profile_keyword_count": 0
        },
        {
          "id": 61970,
          "uuid": "b4671fb0-b7f3-11e8-a0cb-1dfb888e8121",
          "first_name": "JOHN REX",
          "last_name": "NECESARIO",
          "email": "johnrexnecessrio8@gmail.com",
          "phone_num": "9169529817",
          "gender": "male",
          "age": 21,
          "birthdate": null,
          "address": null,
          "postal_code": null,
          "avatar": "https://assets.bossjob.com/users/61970/avatar/oKYOzIx8JA0OTNOoQdXxxEuvbxpuGsnqhjkYNcLN.jpeg",
          "country_key": "ph",
          "region_key": null,
          "location_key": null,
          "website": null,
          "description": null,
          "xp_lvl_key": null,
          "employment_status_key": "employed",
          "referral_code": "johnrex07d41a96",
          "fb_user_id": null,
          "linkedin_user_id": null,
          "is_restricted": false,
          "is_email_verify": false,
          "is_verify": false,
          "is_subscribe": true,
          "status_key": "active",
          "source": "mobile",
          "created_at": "2018-09-14 15:56:36",
          "updated_at": "2019-06-04 23:42:54",
          "active_key": 1,
          "xp_lvl": null,
          "latest_education": {
            "id": 16511,
            "user_id": 61970,
            "school_id": null,
            "school": "University Of Antique-TLMC",
            "degree_key": "Bachelor",
            "field_of_study": "Elementary Education",
            "study_period_from": "2013-06-30",
            "study_period_to": "2018-04-30",
            "grade": "",
            "description": "",
            "location_key": null,
            "country_key": "ph",
            "status_key": "active",
            "is_currently_studying": 0,
            "created_at": "2018-09-14 16:02:35",
            "updated_at": "2018-09-14 16:02:35",
            "degree": "Bachelor",
            "location": null,
            "country": "Philippines"
          },
          "latest_work_xp": null,
          "latest_preference": {
            "id": 16233,
            "user_id": 61970,
            "job_title_id": null,
            "job_title": "Virtual Assistant",
            "location_key": "iloilo_city",
            "salary_range_from": 30000,
            "salary_range_to": 35000,
            "currency": "PHP",
            "job_type_key": "full_time",
            "industry_key": "",
            "country_key": "ph",
            "status_key": "active",
            "created_at": "2018-09-14 16:04:33",
            "updated_at": "2018-09-14 16:04:33",
            "location": "Iloilo City",
            "job_type": "Full-time",
            "country": "Philippines",
            "industry": null
          },
          "recruiter_latest_work_xp": null,
          "country": "Philippines",
          "profile": {
            "percentage": 25,
            "incomplete": [
              "basic_info",
              "website",
              "resume",
              "work_xps",
              "skills"
            ]
          },
          "location": null,
          "resumes": [
            
          ],
          "work_xps": [
            
          ],
          "educations": [
            {
              "country": "Philippines",
              "degree_key": "Bachelor",
              "degree": "Bachelor",
              "description": "",
              "created_at": "2018-09-14 16:02:35",
              "field_of_study": "Elementary Education",
              "school_id": null,
              "country_key": "ph",
              "updated_at": "2018-09-14 16:02:35",
              "user_id": 61970,
              "school": "University Of Antique-TLMC",
              "study_period_to": "2018-04-30",
              "grade": "",
              "is_currently_studying": 0,
              "study_period_from": "2013-06-30",
              "location": null,
              "id": 16511,
              "location_key": null,
              "status_key": "active"
            }
          ],
          "skills": null,
          "roles": [
            {
              "name": "job_seeker",
              "description": "Job seeker",
              "pivot": {
                "user_id": 61970,
                "role_id": 1
              },
              "id": 1,
              "display_name": "Job Seeker"
            }
          ],
          "additional_info": null,
          "user_created_at": "2018-09-14",
          "user_updated_at": "2019-06-04",
          "resumes_count": 0,
          "is_visible": true,
          "device_type": null,
          "is_resume_parsed": 0,
          "last_active_at": {
            "date": "2019-06-04 23:42:54.621657",
            "timezone": "Asia/Singapore",
            "timezone_type": 3
          },
          "google_user_id": null,
          "last_login_ip": null,
          "device_os": null,
          "landing_url": null,
          "google_token": null,
          "is_unlock": true,
          "resume_keyword_count": 0,
          "profile_keyword_count": 0
        },
        {
          "id": 231499,
          "uuid": "263b68f0-5515-11e9-914e-df396c2e8dc7",
          "first_name": "Marjorie",
          "last_name": "Paraiso",
          "email": "mingparaiso@gmail.com",
          "phone_num": null,
          "gender": "",
          "age": 0,
          "birthdate": null,
          "address": null,
          "postal_code": null,
          "avatar": "https://fakeimg.pl/300x300/D6D9DC/4D4D4D/?text=MP&font_size=150&retina=1&font=noto",
          "country_key": "ph",
          "region_key": null,
          "location_key": null,
          "website": null,
          "description": null,
          "xp_lvl_key": null,
          "employment_status_key": "",
          "referral_code": "marjoriefa2ff4b",
          "fb_user_id": null,
          "linkedin_user_id": null,
          "google_user_id": null,
          "google_token": null,
          "is_restricted": false,
          "is_email_verify": false,
          "is_verify": false,
          "is_subscribe": false,
          "is_resume_parsed": 0,
          "status_key": "active",
          "source": "web",
          "created_at": "2019-04-02 15:01:33",
          "updated_at": "2019-04-02 15:01:33",
          "active_key": 1,
          "is_visible": true,
          "xp_lvl": null,
          "latest_education": null,
          "latest_work_xp": null,
          "latest_preference": {
            "job_title_id": null,
            "job_type": "Full-time",
            "country": "Philippines",
            "salary_range_to": 20000,
            "salary_range_from": 15000,
            "created_at": "2019-04-02 15:04:19",
            "industry": null,
            "industry_key": "",
            "job_type_key": "full_time",
            "country_key": "ph",
            "updated_at": "2019-04-02 15:04:19",
            "user_id": 231499,
            "currency": null,
            "location": "Iloilo City",
            "id": 23021,
            "job_title": "Bank Teller",
            "location_key": "iloilo_city",
            "status_key": "active"
          },
          "recruiter_latest_work_xp": null,
          "country": "Philippines",
          "profile": {
            "percentage": 20,
            "incomplete": [
              "avatar",
              "basic_info",
              "website",
              "work_xps",
              "education",
              "skills"
            ]
          },
          "location": null,
          "resumes": [
            {
              "filename": "PARAISO, MARJORIE P. - RESUME.docx",
              "is_active": 1,
              "updated_at": "2019-06-05 00:50:17",
              "user_id": 231499,
              "description": null,
              "is_parsed_es": 0,
              "created_at": "2019-04-02 15:01:35",
              "id": 38266,
              "deleted_at": null,
              "url": "https://assets.bossjob.com/users/231499/resume/phpKkGkNV_1554188494.docx",
              "status_key": "active"
            }
          ],
          "work_xps": [
            
          ],
          "educations": [
            
          ],
          "skills": null,
          "resumes_count": 1,
          "roles": [
            {
              "name": "job_seeker",
              "description": "Job seeker",
              "pivot": {
                "user_id": 231499,
                "role_id": 1
              },
              "id": 1,
              "display_name": "Job Seeker"
            }
          ],
          "additional_info": null,
          "user_created_at": "2019-04-02",
          "user_updated_at": "2019-04-02",
          "resume_education": "Bachelor of Science in Business Administration – Business Management\nWest Visayas State Unioversity, Luna Street, Lapaz, Iloilo City\nJune 2013 – March 2017\nCum Laude\nPersonal information\nAge: 21 years old\nBithdate: February 3, 1997\nBirthplace: Angeles City, Pampanga\nCivil Status: Single\nMother: Marlyn P. Paraiso\nFather: Jose Lemuel O. Paraiso\nREFERENCES\nMARA KRISTI A. SISCAR\nMarketing Specialist\nDBP-Jaro Branch, Iloilo City\n+639335705036\nRONI SHURR KATIPUNAN\nCo-worker\nSunday2pm\n+639302011908\nMARJORIE P. PARAISO\nApplicant",
          "resume_experience": "Admin\nSunday2pm,, Nelly's Building, E Lopez Street, Jaro, Iloilo City\nSept 2017 – October 15, 2018\nManage schedule of activities monthly (TB, Interviews, etc.)\nPerform data entry, review and scan documents\nMulti-tasking with superb accuracy\nStrong sense of urgency and problem solving skills\nAssist in the preparation of regularly scheduled reports and appointments\nScan, sort and file documents\nESL TUTOR\nSunday2pm,, Nelly's Building, E Lopez Street, Jaro, Iloilo City\nApril 2016 – November 15, 2018\nTeach students Basic English\nUpdate and maintain accurate record keeping for daily attendance of the student\nTest, elevate and counsel students with respect with their academic performance\nProvide clear ESL instructions and materials for substitutes\nPurchasing Associate\nMCR Agri-Venture, De Leon Street, Iloilo City\nJuly 2017- Dec 2017\nPeriodically reviews reorder points to ensure they are adequate\nWorks with warehouse and retail management team to ensure adequate stocking space\nStays current in industry and ensure store is stocked with innovative products in demand by our customers\nOperates office and retail equipment in a safe and effective manner – telephones, computers, printer, fax, scanner, etc.\nOn-The-Job Trainee (OJT)\nDevelopment Bank of the Philippines – DBP Jaro Branch\nJun 2016 – Oct 2016\nAssist client and give information about opening an account\nAssist client to fill up forms\nAssist in updating data (individual, brgy. officials and change status)\nAssist in claiming ATM cards",
          "device_type": null,
          "last_active_at": {
            "date": "2019-06-05 00:50:17.630019",
            "timezone": "Asia/Singapore",
            "timezone_type": 3
          },
          "last_login_ip": null,
          "device_os": null,
          "landing_url": null,
          "is_unlock": true,
          "resume_keyword_count": 0,
          "profile_keyword_count": 0
        },
        {
          "id": 225098,
          "uuid": "dd9cbfa0-512d-11e9-8a0a-0fbf7c136e4e",
          "first_name": "Fritz",
          "last_name": "Fernandez",
          "email": "pangga125901@gmail.com",
          "phone_num": null,
          "gender": "",
          "age": 0,
          "birthdate": null,
          "address": null,
          "postal_code": null,
          "avatar": "https://fakeimg.pl/300x300/D6D9DC/4D4D4D/?text=FF&font_size=150&retina=1&font=noto",
          "country_key": "ph",
          "region_key": null,
          "location_key": null,
          "website": null,
          "description": null,
          "xp_lvl_key": null,
          "employment_status_key": "",
          "referral_code": "fritz0f1c9950a3",
          "fb_user_id": null,
          "linkedin_user_id": null,
          "google_user_id": null,
          "google_token": null,
          "is_restricted": false,
          "is_email_verify": false,
          "is_verify": false,
          "is_subscribe": false,
          "is_resume_parsed": 0,
          "status_key": "active",
          "source": "web",
          "created_at": "2019-03-28 15:48:24",
          "updated_at": "2019-03-28 15:48:24",
          "active_key": 1,
          "is_visible": true,
          "xp_lvl": null,
          "latest_education": null,
          "latest_work_xp": null,
          "latest_preference": {
            "job_title_id": "439",
            "job_type": "Contract",
            "country": "Philippines",
            "salary_range_to": 50000,
            "salary_range_from": 30000,
            "created_at": "2019-03-28 15:58:16",
            "industry": "Engineering",
            "industry_key": "engineering",
            "job_type_key": "contract",
            "country_key": "ph",
            "updated_at": "2019-03-28 15:58:54",
            "user_id": 225098,
            "currency": null,
            "location": "Iloilo City",
            "id": 22895,
            "job_title": "Civil Engineer",
            "location_key": "iloilo_city",
            "status_key": "active"
          },
          "recruiter_latest_work_xp": null,
          "country": "Philippines",
          "profile": {
            "percentage": 20,
            "incomplete": [
              "avatar",
              "basic_info",
              "website",
              "work_xps",
              "education",
              "skills"
            ]
          },
          "location": null,
          "resumes": [
            {
              "filename": "Civil Engineer Fritz Fernandez CV.pdf",
              "is_active": 1,
              "updated_at": "2019-06-05 00:47:27",
              "user_id": 225098,
              "description": null,
              "is_parsed_es": 0,
              "created_at": "2019-03-28 15:48:34",
              "id": 37068,
              "deleted_at": null,
              "url": "https://assets.bossjob.com/users/225098/resume/ZRHiqlTkSGbYtfTo3kutIDMbr78wvCsV3LYis0zU.pdf",
              "status_key": "active"
            }
          ],
          "work_xps": [
            
          ],
          "educations": [
            
          ],
          "skills": null,
          "resumes_count": 1,
          "roles": [
            {
              "name": "job_seeker",
              "description": "Job seeker",
              "pivot": {
                "user_id": 225098,
                "role_id": 1
              },
              "id": 1,
              "display_name": "Job Seeker"
            }
          ],
          "additional_info": null,
          "user_created_at": "2019-03-28",
          "user_updated_at": "2019-03-28",
          "resume_skills": "(WlT)\n, Offlcers Candidate School (OCS),\nTRADOC, Tarlac,2005\nu Bachelor of Science in Civil\nEngineering, 2003\nWestem lnstitute of Technology (WlT)\nPROFESSIONAL MEMBERSHIP AND\nAFFILIATION\n. MemberoiSaudiCouncilof Engineer,\nSCE #210543, Kingdom of Saudi\nArabia\nMember of lnstitution of Engineers\nPNG lnc., IEPNG #9614, Papua New\nGuinea\n\" Professional EngineersRegistration\nBoard, PERB i14969, Papua New\nGuinea\n,, ISO 21500 Lead Project Management,\n(PMLPRMl 01 4368-201 7-1 0)\nProfessional Evaluation Certifi cation\nBoard (PECB), Canada\n' lS0 31000 Risk Management,\n(RMRM1 0'14368-201 7-10)\nProfessional Evaluation Certification\nBoard (PECB), Canada\nMaster Plumber, #5591\nProfessional Regulation Commission\n(PRC), Philippines\nFRITZ ROBLES FERNANDEZ(WlT)\nPROFESSIONAL MEMBERSHIP AND\nAFFILIATION\n. MemberoiSaudiCouncilof Engineer,\nSCE #210543, Kingdom of Saudi\nArabia\nMember of lnstitution of Engineers\nPNG lnc., IEPNG #9614, Papua New\nGuinea\n\" Professional EngineersRegistration\nBoard, PERB i14969, Papua New\nGuinea\n,, ISO 21500 Lead Project Management,\n(PMLPRMl 01 4368-201 7-1 0)\nProfessional Evaluation Certifi cation\nBoard (PECB), Canada\n' lS0 31000 Risk Management,\n(RMRM1 0'14368-201 7-10)\nProfessional Evaluation Certification\nBoard (PECB), Canada\nMaster Plumber, #5591\nProfessional Regulation Commission\n(PRC), Philippines\nFRITZ ROBLES FERNANDEZ",
          "resume_experience": "S:\n* The Mansion, lloilo City, Philippines (2019-Current) - Duty Engineer. Responsible to\nlead/organizelsupports the Engineering Team to efficiently maintain all hotel operations\nsuch that in house improvements, general safety, security and maintenance work.\n. AGL Builders, Port Moresby, Papua New Guinea (2017-2018) - Buiiding & Construction\nManager. Family and Sexual Violence Uni1, Waigani; Construction of site development,\ngeneral services and external site works. A Cardno-managed and Australian Govemment\nfunded Justice Services and Stability for Development; Nambawan Super Koki Housing\ntwenty{wo (22) units staff houses including site development, general services and\nexternal site works,\nAlmarai (FMCG), Kingdom of Saudi Arabia, KSA {.2014-20171- Projecl Engineer (Civil),\nworked as client representative to their EPC coniractors for the successful delivery of\nturnkey projects such as: Central Processing Plant-3 2017; Effluent/Sewer Treatment Plant\n2017, Accommodation Building 200 person capacity 2016; Cheese Plant\nExpansionlWarehouse-CHPA 20'15 Central Processing Planl2; BMG-Ladies Facility\nExpansion 2014 Cenkal Processing Plant-2.\nCorps of Engineer, Armed Forces of the Philippines (2004-2014) - Rank (Captain).\nlnvolves with govemment funded projects as part of pro.iect management teamlproject\nadministrator and inspector of projects that includes: Brigade's Retraining Facilities 2014,\nPacific Patuership 2012, PP12 Engineering Civic Action Projects (ENCAP); S-units, 10-\nDoor, 2-Storey Apartment 2010, Mactan-Benito Ebuen Air Base, Cebu, Philippines;\nKalayaan Barangay Program 2008, lnter-lsland Projects: Road, Water System, School\nBuildings and Health Centers (Region Vl, Vll & Vlll Prolects); 2-units, S-Storey Army\nTransient Facility 2006, Forl Andres Bonifacio, Taguig, Manila, Philippines.\n. WYKO Builders Construction Company, Philippines (2003'2004) - Quantity Surveyor\nfor Community Shopping Complex 20M, Sta. Cruz, Laguna, Philippines.\nPERSONAL INFORMATION:\nAddress: Lot 5, Block 5, Phase 2, Lumina Homes, Brgy. Abilay Norte, Oton, lloilo\nBirth Bate: 29 April 1980\nCivil Status: Married\nAge: 38 years old\nGender: Male",
          "resume_technology": "(WlT)\n, Offlcers Candidate School (OCS),\nTRADOC, Tarlac,2005\nu Bachelor of Science in Civil\nEngineering, 2003\nWestem lnstitute of Technology (WlT)\nPROFESSIONAL MEMBERSHIP AND\nAFFILIATION\n. MemberoiSaudiCouncilof Engineer,\nSCE #210543, Kingdom of Saudi\nArabia\nMember of lnstitution of Engineers\nPNG lnc., IEPNG #9614, Papua New\nGuinea\n\" Professional EngineersRegistration\nBoard, PERB i14969, Papua New\nGuinea\n,, ISO 21500 Lead Project Management,\n(PMLPRMl 01 4368-201 7-1 0)\nProfessional Evaluation Certifi cation\nBoard (PECB), Canada\n' lS0 31000 Risk Management,\n(RMRM1 0'14368-201 7-10)\nProfessional Evaluation Certification\nBoard (PECB), Canada\nMaster Plumber, #5591\nProfessional Regulation Commission\n(PRC), Philippines\nFRITZ ROBLES FERNANDEZ(WlT)\nPROFESSIONAL MEMBERSHIP AND\nAFFILIATION\n. MemberoiSaudiCouncilof Engineer,\nSCE #210543, Kingdom of Saudi\nArabia\nMember of lnstitution of Engineers\nPNG lnc., IEPNG #9614, Papua New\nGuinea\n\" Professional EngineersRegistration\nBoard, PERB i14969, Papua New\nGuinea\n,, ISO 21500 Lead Project Management,\n(PMLPRMl 01 4368-201 7-1 0)\nProfessional Evaluation Certifi cation\nBoard (PECB), Canada\n' lS0 31000 Risk Management,\n(RMRM1 0'14368-201 7-10)\nProfessional Evaluation Certification\nBoard (PECB), Canada\nMaster Plumber, #5591\nProfessional Regulation Commission\n(PRC), Philippines\nFRITZ ROBLES FERNANDEZ",
          "device_type": null,
          "last_active_at": {
            "date": "2019-06-05 00:47:27.274116",
            "timezone": "Asia/Singapore",
            "timezone_type": 3
          },
          "last_login_ip": null,
          "device_os": null,
          "landing_url": null,
          "is_unlock": true,
          "resume_keyword_count": 0,
          "profile_keyword_count": 0
        },
        {
          "id": 85791,
          "uuid": "4942f5f0-eed2-11e8-8663-376b2191bca0",
          "first_name": "Zarena",
          "last_name": "Tabuena",
          "email": "zmtabuena@gmail.com",
          "phone_num": null,
          "gender": "",
          "age": 0,
          "birthdate": null,
          "address": null,
          "postal_code": null,
          "avatar": "https://fakeimg.pl/300x300/D6D9DC/4D4D4D/?text=ZT&font_size=150&retina=1&font=noto",
          "country_key": "ph",
          "region_key": null,
          "location_key": null,
          "website": null,
          "description": null,
          "xp_lvl_key": null,
          "employment_status_key": "",
          "referral_code": "zarenad2bba8273",
          "fb_user_id": "201481597408318",
          "linkedin_user_id": null,
          "is_restricted": false,
          "is_email_verify": false,
          "is_verify": false,
          "is_subscribe": true,
          "status_key": "active",
          "source": "web",
          "created_at": "2018-11-23 11:45:57",
          "updated_at": "2018-11-23 12:06:26",
          "active_key": 1,
          "is_visible": true,
          "xp_lvl": null,
          "latest_education": null,
          "latest_work_xp": null,
          "latest_preference": {
            "job_title_id": "74",
            "job_type": "Full-time",
            "country": "Philippines",
            "salary_range_to": 15000,
            "salary_range_from": 10000,
            "created_at": "2018-11-23 12:13:49",
            "industry": null,
            "industry_key": "",
            "job_type_key": "full_time",
            "country_key": "ph",
            "updated_at": "2018-11-23 12:16:18",
            "user_id": 85791,
            "currency": null,
            "location": "Iloilo City",
            "id": 18774,
            "job_title": "Accounting Staff",
            "location_key": "iloilo_city",
            "status_key": "active"
          },
          "recruiter_latest_work_xp": null,
          "country": "Philippines",
          "profile": {
            "percentage": 20,
            "incomplete": [
              "avatar",
              "basic_info",
              "website",
              "work_xps",
              "education",
              "skills"
            ]
          },
          "location": null,
          "resumes": [
            {
              "filename": "Resume... ACCOUNTING ASSISTANT..RED.pdf",
              "is_active": 1,
              "updated_at": "2019-06-04 23:31:09",
              "user_id": 85791,
              "description": null,
              "is_parsed_es": 0,
              "created_at": "2018-11-23 12:06:03",
              "id": 11766,
              "deleted_at": null,
              "url": "https://assets.bossjob.com/users/85791/resume/7Ky2JDFBq8vXg2Z08gDTp7FIplnktLOYbX4M7UjA.pdf",
              "status_key": "active"
            }
          ],
          "work_xps": [
            
          ],
          "educations": [
            
          ],
          "skills": null,
          "roles": [
            {
              "name": "job_seeker",
              "description": "Job seeker",
              "pivot": {
                "user_id": 85791,
                "role_id": 1
              },
              "id": 1,
              "display_name": "Job Seeker"
            }
          ],
          "additional_info": null,
          "user_created_at": "2018-11-23",
          "user_updated_at": "2018-11-23",
          "resumes_count": 1,
          "resume_technology": "BACHELOR OF SCIENCE IN ACCOUNTANCY 2010 - 2013 CENTRAL\nPHILIPPINE UNIVERSITY\nSECONDARY LEVEL 2006 - 2010 NUMANCIA INTEGRATED\nSCHOOL\nREFERENCES\nJOEMER M. DINERO\nAudit Head\nPhone Number: 09072179297\nSTEPHANIE GIEL CANDELARIO\nHuman Resource\nPhone Number: 09482379765\nKRESHA LARA DALIDA\nAccounting Associate\nPhone Number: 09090397909",
          "resume_education": "BACHELOR OF SCIENCE IN ACCOUNTANCY 2013 - 2015 GARCIA\nCOLLEGE OF TECHNOLOGY\nBACHELOR OF SCIENCE IN ACCOUNTANCY 2010 - 2013 CENTRAL\nPHILIPPINE UNIVERSITY\nSECONDARY LEVEL 2006 - 2010 NUMANCIA INTEGRATED\nSCHOOL\nREFERENCES\nJOEMER M. DINERO\nAudit Head\nPhone Number: 09072179297\nSTEPHANIE GIEL CANDELARIO\nHuman Resource\nPhone Number: 09482379765\nKRESHA LARA DALIDA\nAccounting Associate\nPhone Number: 09090397909",
          "resume_skills": "BACHELOR OF SCIENCE IN ACCOUNTANCY 2010 - 2013 CENTRAL\nPHILIPPINE UNIVERSITY\nSECONDARY LEVEL 2006 - 2010 NUMANCIA INTEGRATED\nSCHOOL\nREFERENCES\nJOEMER M. DINERO\nAudit Head\nPhone Number: 09072179297\nSTEPHANIE GIEL CANDELARIO\nHuman Resource\nPhone Number: 09482379765\nKRESHA LARA DALIDA\nAccounting Associate\nPhone Number: 09090397909",
          "resume_experience": "ACCOUNTING ASSOCIATE SOUTHWEST TOURS (BORACAY), INC.\nJUNE 14 – OCTOBER 31, 2017\nRecords daily sales and disbursements through\nQuickBooks.\nPrepares checks and check vouchers for the payment\nof supplies, utilities and BIR transactions.\nIssues checks to suppliers.\nMonitors of checks already issued through Microsoft\nExcel.\nSegregates of paid vouchers from unpaid by filing it in\na separate folder.\nConducts surprise inventory count and cash count\nevery month.\nFiling of Monthly and Quarterly Value Added Tax\nReturn.\nPrepares a computation of payroll and pay slip for the\nemployees.\nPetty Cash Custodian.\nBank Reconciliation\nACCOUNTING ASSOCIATE RCCE PUBLISHING AND PROMOTIONS\nJUNE 14 – OCTOBER 31, 2017\nMaintains records of daily sales and disbursements\nthrough QuickBooks.\nPrepares checks and check vouchers for the payment\nof necessary expenses (ex. SSS, PhilHeath and SSS).\nMaintains records of checks issued through Microsoft\nExcel.\nFiling of Percentage Tax Return.\nPrepares a computation for payroll and pay slip for\nthe employee.\nSeparates paid vouchers from unpaid by filing in a\nseparate folder.\nACCOUNTING ASSOCIATE KALIBO TOURISM VENTURES, INC.\nJUNE 14 – OCTOBER 31, 2017\nConducts surprise inventory count.\nRecords daily sales and disbursements through\nQuickBooks.\nFiling of Monthly Percentage Tax Return.\nPrepares a computation of payroll and pay slip for the\nemployees.\nMonitors of checks already issued through Microsoft\nExcel.",
          "device_type": null,
          "is_resume_parsed": 0,
          "last_active_at": {
            "date": "2019-06-04 23:31:09.141888",
            "timezone": "Asia/Singapore",
            "timezone_type": 3
          },
          "google_user_id": null,
          "last_login_ip": null,
          "device_os": null,
          "landing_url": null,
          "google_token": null,
          "is_unlock": true,
          "resume_keyword_count": 0,
          "profile_keyword_count": 0
        }
      ],
      "max_score": null,
      "page": 4,
      "total_pages": 4,
      "size": 100,
      "total_num": 306,
      "sort": 1,
      "query": null,
      "params": "job_location=iloilo_city%2Cpassi%2Croxas"
    },
    "status_code": 200
  }